dash_express/__init__.py
dash_express/_app_shell.py
dash_express/preview_chart.py
dash_express/version.py
dash_express/filters/__init__.py
dash_express/filters/autofilter.py
dash_express/filters/filterfunc.py
dash_express/kpi/__init__.py
dash_express-1.2.0.dist-info/LICENSE
dash_express-1.2.0.dist-info/METADATA
dash_express-1.2.0.dist-info/WHEEL
dash_express-1.2.0.dist-info/top_level.txt
dash_express-1.2.0.dist-info/RECORD
