Metadata-Version: 2.1
Name: dash_express
Version: 1.2.0
Summary: A tool for faster application development Plotly Dash
Home-page: https://github.com/stpnvkirill/dash-express
Author: Kirill Stepanov
Author-email: stpnv.kirill.o@gmail.com
Classifier: Programming Language :: Python :: 3
Classifier: License :: OSI Approved :: MIT License
Classifier: Operating System :: OS Independent
License-File: LICENSE
Requires-Dist: dash >=2.11.1
Requires-Dist: pandas >=2.0.3
Requires-Dist: orjson >=3.9.2
Requires-Dist: dash-iconify ==0.1.2
Requires-Dist: dash-leaflet ==0.1.28
Requires-Dist: flask-caching >=2.0.2
Requires-Dist: dash-mantine-components ==0.12.1
